gpt_prompt/__init__.py
gpt_prompt/base/__init__.py
gpt_prompt/base/base_class.py
gpt_prompt/character/Astrologer.py
gpt_prompt/character/__init__.py
gpt_prompt/character/aI_doctor.py
gpt_prompt/character/accountant.py
gpt_prompt/character/advertiser.py
gpt_prompt/character/ceo.py
gpt_prompt/character/composer.py
gpt_prompt/character/cospalyer.py
gpt_prompt/character/database_expert.py
gpt_prompt/character/debater.py
gpt_prompt/character/dialogue.py
gpt_prompt/character/dream_interpreter.py
gpt_prompt/character/drunk.py
gpt_prompt/character/english_pronunciation_helper.py
gpt_prompt/character/film_critic.py
gpt_prompt/character/football_commentator.py
gpt_prompt/character/interviewer.py
gpt_prompt/character/it_architect.py
gpt_prompt/character/math_teacher.py
gpt_prompt/character/mongo_tom_prompt.py
gpt_prompt/character/motivational_coach.py
gpt_prompt/character/motivational_speaker.py
gpt_prompt/character/novelist.py
gpt_prompt/character/nutritionist.py
gpt_prompt/character/parenting_assistant.py
gpt_prompt/character/philosopher.py
gpt_prompt/character/philosophy_teacher.py
gpt_prompt/character/poet.py
gpt_prompt/character/rapper.py
gpt_prompt/character/relationship_coach.py
gpt_prompt/character/resume_optimizer.py
gpt_prompt/character/screenwriter.py
gpt_prompt/character/seller.py
gpt_prompt/character/translator.py
gpt_prompt/character/wise_council.py
gpt_prompt/character/writing_assistant.py
gpt_prompt/cosplay/__init__.py
gpt_prompt/cosplay/buddha_guidance.py
gpt_prompt/cosplay/magic_conch.py
gpt_prompt/cosplay/socrates.py
gpt_prompt/cosplay/uchiha_itachi.py
gpt_prompt/game/__init__.py
gpt_prompt/game/gomoku_prompt.py
gpt_prompt/game/life_simulation.py
gpt_prompt/game/text_adventure.py
gpt_prompt/game/tic_tac_toe.py
gpt_prompt/tools/__init__.py
gpt_prompt/tools/anti_dan.py
gpt_prompt/tools/developer_mode.py
gpt_prompt/tools/domain_generator.py
gpt_prompt/tools/emoji_translation.py
gpt_prompt/tools/excel.py
gpt_prompt/tools/faqs_generator.py
gpt_prompt-0.0.11.dist-info/LICENSE
gpt_prompt-0.0.11.dist-info/METADATA
gpt_prompt-0.0.11.dist-info/WHEEL
gpt_prompt-0.0.11.dist-info/top_level.txt
gpt_prompt-0.0.11.dist-info/RECORD
